setup.py
datastore/__init__.py
datastore.egg-info/PKG-INFO
datastore.egg-info/SOURCES.txt
datastore.egg-info/dependency_links.txt
datastore.egg-info/namespace_packages.txt
datastore.egg-info/requires.txt
datastore.egg-info/top_level.txt
datastore/core/__init__.py
datastore/core/basic.py
datastore/core/key.py
datastore/core/query.py
datastore/core/serialize.py
datastore/core/test/__init__.py
datastore/core/test/test_basic.py
datastore/core/test/test_key.py
datastore/core/test/test_query.py
datastore/core/test/test_serialize.py
datastore/core/util/__init__.py
datastore/core/util/fasthash.py
datastore/filesystem/__init__.py
datastore/filesystem/test.py