Metadata-Version: 1.0
Name: datastore
Version: 0.3.5
Summary: simple, unified API for multiple data stores
Home-page: http://github.com/datastore/datastore
Author: Juan Batiz-Benet
Author-email: juan@benet.ai
License: MIT License
Keywords: datastore,unified api,database
Platform: UNKNOWN
Classifier: Topic :: Database
Classifier: Topic :: Database :: Front-Ends
